calculator/__init__.py
calculator/calculator.py
simplecalculator_ganesan-0.4.0.dist-info/METADATA
simplecalculator_ganesan-0.4.0.dist-info/WHEEL
simplecalculator_ganesan-0.4.0.dist-info/top_level.txt
simplecalculator_ganesan-0.4.0.dist-info/RECORD
