Metadata-Version: 2.4
Name: simplecalculator-ganesan
Version: 0.4.0
Summary: A simple calculator package
Author: Ganesan Selvaraj
Author-email: ganesanluna@yahoo.in
Classifier: Programming Language :: Python :: 3
Classifier: License :: OSI Approved :: MIT License
Classifier: Operating System :: OS Independent
Requires-Python: >=3.6
Dynamic: author
Dynamic: author-email
Dynamic: classifier
Dynamic: description
Dynamic: description-content-type
Dynamic: requires-python
Dynamic: summary
